{
  "objekt": {
    "id": "1374",
    "straße": "Birkenstr. 41",
    "stadt": "Berlin",
    "plz": "10342",
    "mieter": "multi-tenant",
    "singletenant": false,
    "baurecht": {
    "baugenehmigung": "1374/baugenehmigung.pdf",
    "brandschutzkonzept": "1374/brandschutzkonzept.pdf"
    },
    "prüfsv": {
      "brandmeldeanlageanlage": {
        "0prüfung": "2019-05-29",
        "0prüfungsbericht": "1374/0_sv_bma.pdf",
        "1prüfung": "2022-05-27",
        "1prüfungsbericht": "1374/1_sv_bma.pdf",
        "nächsteprüfung": "2025-05-27"
      },
      "Rauchabzugsanlage": {
        "0prüfung": "2019-05-19",
        "0prüfungsbericht": "1374/0_sv_rva.pdf",
        "1prüfung": "2022-05-20",
        "1prüfungsbericht": "1374/1_sv_rva.pdf",
        "nächsteprüfung": "2025-05-20"
      }
    }
  }
}

